pytest_sample_argvalues/__init__.py
pytest_sample_argvalues/main.py
pytest_sample_argvalues-0.0.1.dist-info/LICENSE
pytest_sample_argvalues-0.0.1.dist-info/METADATA
pytest_sample_argvalues-0.0.1.dist-info/WHEEL
pytest_sample_argvalues-0.0.1.dist-info/top_level.txt
pytest_sample_argvalues-0.0.1.dist-info/RECORD
