Metadata-Version: 2.1
Name: pytest-sample-argvalues
Version: 0.0.1
Summary: A utility function to help choose a random sample from your argvalues in pytest.
Author: Adam Powis
License: MIT License
Classifier: License :: OSI Approved :: MIT License
Requires-Python: >=3.8.0
License-File: LICENSE
Requires-Dist: iteration-utilities
Requires-Dist: pytest
Provides-Extra: test
Requires-Dist: pylint ; extra == 'test'
